README.md
setup.py
ginteract/__init__.py
ginteract/interact.py
ginteract/main.py
ginteract/test_main.py
ginteract.egg-info/PKG-INFO
ginteract.egg-info/SOURCES.txt
ginteract.egg-info/dependency_links.txt
ginteract.egg-info/entry_points.txt
ginteract.egg-info/requires.txt
ginteract.egg-info/top_level.txt