Metadata-Version: 1.0
Name: ginteract
Version: 0.2.2
Summary: An interactive Git client!
Home-page: http://github.com/jacsmith21/ginteract
Author: Jacob Smith
Author-email: jacob.smith@unb.ca
License: MIT
Platform: UNKNOWN
